graph/__init__.py
graph/interface.py
graph/retworkx/__init__.py
graph/retworkx/api.py
graph/retworkx/digraph.py
graph/retworkx/str_digraph.py
graph/viz/__init__.py
graph/viz/graphviz.py
graph/viz/prelude.py
graph/viz/texttree.py
graph_wrapper-1.8.0.dist-info/LICENSE
graph_wrapper-1.8.0.dist-info/METADATA
graph_wrapper-1.8.0.dist-info/WHEEL
graph_wrapper-1.8.0.dist-info/RECORD
